CHANGES.txt
README.txt
setup.cfg
setup.py
buildout/__init__.py
buildout.eggnest.egg-info/PKG-INFO
buildout.eggnest.egg-info/SOURCES.txt
buildout.eggnest.egg-info/dependency_links.txt
buildout.eggnest.egg-info/entry_points.txt
buildout.eggnest.egg-info/namespace_packages.txt
buildout.eggnest.egg-info/not-zip-safe
buildout.eggnest.egg-info/requires.txt
buildout.eggnest.egg-info/top_level.txt
buildout/eggnest/__init__.py
buildout/eggnest/eggnest.py
buildout/eggnest/eggnest.txt
buildout/eggnest/tests.py
docs/HISTORY.txt
docs/product.txt