Metadata-Version: 1.0
Name: buildout.eggnest
Version: 0.1
Summary: buildout extension to auto install eggs
Home-page: http://svn.plone.org/svn/collective/buildout/buildout.eggnest
Author: Martin Lundwall
Author-email: martin@betahaus.net
License: GPL
Keywords: buildout extension auto install
Platform: UNKNOWN
Classifier: Framework :: Buildout
Classifier: Intended Audience :: Developers
Classifier: Topic :: Software Development :: Build Tools
Classifier: Topic :: Software Development :: Libraries :: Python Modules
